vb_ihmm
