Metadata-Version: 1.0
Name: vbihmm
Version: 1.02
Summary: Set of classes to support inference in mixture models and HMMs with Gaussian and multinomial observations.
